LICENSE
MANIFEST.in
README.rst
consul_decouple.py
setup.py
consul_decouple.egg-info/PKG-INFO
consul_decouple.egg-info/SOURCES.txt
consul_decouple.egg-info/dependency_links.txt
consul_decouple.egg-info/not-zip-safe
consul_decouple.egg-info/requires.txt
consul_decouple.egg-info/top_level.txt