Metadata-Version: 1.1
Name: consul-decouple
Version: 0.0.2
Summary: An extension for python-decouple to read Consul using python-consul2.
Home-page: https://github.com/lucasrcezimbra/consul-decouple
Author: Lucas Rangel Cezimbra
Author-email: lucas@cezimbra.tec.br
License: LGPLv2
Keywords: consul,decouple,python-decouple,python-consul,python-consul2
Platform: UNKNOWN
Classifier: Development Status :: 4 - Beta
Classifier: Intended Audience :: Developers
Classifier: License :: OSI Approved :: GNU Lesser General Public License v2 (LGPLv2)
Classifier: Programming Language :: Python :: 3
Classifier: Programming Language :: Python :: 3 :: Only
Classifier: Topic :: Software Development :: Libraries
